codestory/__init__.py
codestory/cli.py
codestory/commit_formats.py
codestory/config.py
codestory/debug_script.py
codestory/git_utils.py
codestory/llm_utils.py
tests/__init__.py
tests/test_commit_formats.py
tests/test_git_utlis.py
codestory-0.1.0.dist-info/METADATA
codestory-0.1.0.dist-info/WHEEL
codestory-0.1.0.dist-info/entry_points.txt
codestory-0.1.0.dist-info/top_level.txt
codestory-0.1.0.dist-info/RECORD
